b4r/__init__.py
b4r/pipe/CreateMs2.py
b4r/pipe/LibB4Rtools.py
b4r/pipe/__init__.py
b4r/pipe/b4rquery.py
b4r/pipe/godec.py
b4r/pipe/main.py
b4r/pipe/makedatalist.py
b4r/pipe/specfile4.py
b4r-2024.7.0.dist-info/LICENSE
b4r-2024.7.0.dist-info/METADATA
b4r-2024.7.0.dist-info/WHEEL
b4r-2024.7.0.dist-info/RECORD
