Metadata-Version: 2.1
Name: b4r
Version: 2024.7.0
Summary: Reduction and analysis tools for LMT/B4R
License: MIT
Author: Akio Taniguchi
Author-email: taniguchi@a.phys.nagoya-u.ac.jp
Requires-Python: >=3.9,<3.12
Classifier: License :: OSI Approved :: MIT License
Classifier: Programming Language :: Python :: 3
Classifier: Programming Language :: Python :: 3.9
Classifier: Programming Language :: Python :: 3.10
Classifier: Programming Language :: Python :: 3.11
Requires-Dist: astropy (>=6.0,<7.0)
Requires-Dist: matplotlib (>=3.8,<4.0)
Requires-Dist: netcdf4 (>=1.6,<2.0)
Requires-Dist: numpy (>=1.26,<2.0)
Requires-Dist: python-casacore (>=3.5,<4.0)
Requires-Dist: scikit-learn (>=1.4,<2.0)
Requires-Dist: scipy (>=1.13,<2.0)
Requires-Dist: tqdm (>=4.66,<5.0)
